<?xml version="1.0" encoding="UTF-8"?>
<objects serializationModel="Studio.02.02.00">
	<object class="AudioFile" id="{bd0855d2-8184-4649-9b52-9f9a0d45c842}">
		<property name="assetPath">
			<value>roll/roll-004.wav</value>
		</property>
		<property name="frequencyInKHz">
			<value>48</value>
		</property>
		<property name="channelCount">
			<value>1</value>
		</property>
		<property name="length">
			<value>1.0854166666666667</value>
		</property>
		<relationship name="masterAssetFolder">
			<destination>{9e6bdf9e-bfae-4bd7-ad69-017ec799a7fe}</destination>
		</relationship>
	</object>
</objects>
